Metadata-Version: 1.1
Name: azure-alerts-plugin
Version: 0.1.6
Summary: check active azure alerts
Home-page: https://github.com/CoffeeITWorks/nagios_azure_alerts
Author: Matias Graña
Author-email: maicolmatiasg@gmail.com
License: MIT
Platform: UNKNOWN
Classifier: Development Status :: 5 - Production/Stable
Classifier: Intended Audience :: System Administrators
Classifier: License :: OSI Approved :: MIT License
Classifier: Programming Language :: Python :: 3
Classifier: Programming Language :: Python :: 3 :: Only
Classifier: Topic :: System :: Monitoring
